domainlab/.gitignore
domainlab/.pylintrc
domainlab/__init__.py
domainlab/algos/__init__.py
domainlab/algos/a_algo_builder.py
domainlab/algos/builder_api_model.py
domainlab/algos/builder_custom.py
domainlab/algos/builder_dann.py
domainlab/algos/builder_diva.py
domainlab/algos/builder_erm.py
domainlab/algos/builder_hduva.py
domainlab/algos/builder_jigen1.py
domainlab/algos/msels/__init__.py
domainlab/algos/msels/a_model_sel.py
domainlab/algos/msels/c_msel_oracle.py
domainlab/algos/msels/c_msel_tr_loss.py
domainlab/algos/msels/c_msel_val.py
domainlab/algos/observers/__init__.py
domainlab/algos/observers/a_observer.py
domainlab/algos/observers/b_obvisitor.py
domainlab/algos/observers/c_obvisitor_cleanup.py
domainlab/algos/observers/c_obvisitor_gen.py
domainlab/algos/trainers/__init__.py
domainlab/algos/trainers/a_trainer.py
domainlab/algos/trainers/args_dial.py
domainlab/algos/trainers/args_miro.py
domainlab/algos/trainers/compos/__init__.py
domainlab/algos/trainers/compos/matchdg_args.py
domainlab/algos/trainers/compos/matchdg_match.py
domainlab/algos/trainers/compos/matchdg_utils.py
domainlab/algos/trainers/hyper_scheduler.py
domainlab/algos/trainers/mmd_base.py
domainlab/algos/trainers/train_basic.py
domainlab/algos/trainers/train_causIRL.py
domainlab/algos/trainers/train_coral.py
domainlab/algos/trainers/train_dial.py
domainlab/algos/trainers/train_ema.py
domainlab/algos/trainers/train_fishr.py
domainlab/algos/trainers/train_hyper_scheduler.py
domainlab/algos/trainers/train_irm.py
domainlab/algos/trainers/train_matchdg.py
domainlab/algos/trainers/train_miro.py
domainlab/algos/trainers/train_miro_model_wraper.py
domainlab/algos/trainers/train_miro_utils.py
domainlab/algos/trainers/train_mldg.py
domainlab/algos/trainers/zoo_trainer.py
domainlab/algos/utils.py
domainlab/algos/zoo_algos.py
domainlab/arg_parser.py
domainlab/cli.py
domainlab/compos/__init__.py
domainlab/compos/a_nn_builder.py
domainlab/compos/builder_nn_alex.py
domainlab-0.7.1.dist-info/LICENSE
domainlab-0.7.1.dist-info/METADATA
domainlab-0.7.1.dist-info/WHEEL
domainlab-0.7.1.dist-info/entry_points.txt
domainlab-0.7.1.dist-info/RECORD
