Metadata-Version: 2.1
Name: domainlab
Version: 0.7.1
Summary: Library of modular domain generalization for deep learning
Home-page: https://marrlab.github.io/DomainLab/
Author: Xudong Sun
Author-email: smilesun.east@gmail.com
Requires-Python: >=3.9,<4.0
Classifier: Programming Language :: Python :: 3
Classifier: Programming Language :: Python :: 3.9
Classifier: Programming Language :: Python :: 3.10
Classifier: Programming Language :: Python :: 3.11
Classifier: Programming Language :: Python :: 3.12
Classifier: Programming Language :: Python :: 3.13
Requires-Dist: backpack-for-pytorch (>=1.6.0,<2.0.0)
Requires-Dist: gdown (>=4.7.1,<5.0.0)
Requires-Dist: matplotlib (>=3.9.0,<4.0.0)
Requires-Dist: numpy (>=1.23.4,<2.0.0)
Requires-Dist: pandas (>=1.5.1,<2.0.0)
Requires-Dist: pillow (>=9.3.0,<10.0.0)
Requires-Dist: pyyaml (>=6.0,<7.0)
Requires-Dist: rich (>=13.3.1,<14.0.0)
Requires-Dist: scikit-learn (>=1.2.1,<2.0.0)
Requires-Dist: seaborn (>=0.13.2,<0.14.0)
Requires-Dist: setuptools (>=69.5.1,<70.0.0)
Requires-Dist: torch (>=1.12.0,<2.0.0)
Requires-Dist: torchmetrics (>=0.10.0,<0.11.0)
Requires-Dist: torchvision (>=0.13.0,<0.14.0)
Project-URL: Repository, https://github.com/marrlab/DomainLab
